tyype/__init__.py
tyype/datey.py
tyype/floaty.py
tyype/inty.py
tyype-0.0.3.0.dist-info/LICENSE
tyype-0.0.3.0.dist-info/METADATA
tyype-0.0.3.0.dist-info/WHEEL
tyype-0.0.3.0.dist-info/top_level.txt
tyype-0.0.3.0.dist-info/RECORD
