Metadata-Version: 2.1
Name: tyype
Version: 0.0.3.0
Summary: Pacote utilizado para tratar a entrada padrão
Home-page: https://github.com/renansilva15/tyype
Author: Renan Gabriel Gonçalves Silva
Author-email: renangabrielsilva150@gmail.com
License: UNKNOWN
Project-URL: Bug Tracker, https://github.com/renansilva15/tyype
Platform: UNKNOWN
Classifier: Programming Language :: Python :: 3
Classifier: License :: OSI Approved :: MIT License
Classifier: Operating System :: OS Independent
Requires-Python: >=3.8
License-File: LICENSE
